{
    "xsappname": "galactic-spacefarer-app",
    "tenant-mode": "shared",
    "scopes": [
      {
        "name": "$XSAPPNAME.User",
        "description": "Default scope for users"
      },
      {
        "name": "$XSAPPNAME.PlanetXAccess",
        "description": "Scope for users from Planet X"
      }
    ],
    "attributes": [
      {
        "name": "homePlanet",
        "description": "The planet where the user comes from",
        "valueType": "string"
      }
    ],
    "roles": [
      {
        "name": "User",
        "description": "Default role for users",
        "scopes": [
          "$XSAPPNAME.User"
        ]
      },
      {
        "name": "PlanetXUser",
        "description": "Role for users from Planet X",
        "scopes": [
          "$XSAPPNAME.PlanetXAccess"
        ],
        "attributes": [
          {
            "name": "homePlanet",
            "value": "X"
          }
        ]
      }
    ]
  }
  